MANIFEST.in
setup.py
src/asm/__init__.py
src/asm.cmsui.egg-info/PKG-INFO
src/asm.cmsui.egg-info/SOURCES.txt
src/asm.cmsui.egg-info/dependency_links.txt
src/asm.cmsui.egg-info/not-zip-safe
src/asm.cmsui.egg-info/requires.txt
src/asm.cmsui.egg-info/top_level.txt
src/asm/cmsui/__init__.py
src/asm/cmsui/asset.py
src/asm/cmsui/base.py
src/asm/cmsui/cms.py
src/asm/cmsui/configure.zcml
src/asm/cmsui/edition.py
src/asm/cmsui/form.py
src/asm/cmsui/format.py
src/asm/cmsui/ftesting.zcml
src/asm/cmsui/homepage.py
src/asm/cmsui/htmlpage.py
src/asm/cmsui/importer.py
src/asm/cmsui/interfaces.py
src/asm/cmsui/layout.py
src/asm/cmsui/news.py
src/asm/cmsui/page.py
src/asm/cmsui/preview.py
src/asm/cmsui/redirect.py
src/asm/cmsui/replace.py
src/asm/cmsui/retail.py
src/asm/cmsui/search.py
src/asm/cmsui/security.py
src/asm/cmsui/security.txt
src/asm/cmsui/testing.py
src/asm/cmsui/tinymce.py
src/asm/cmsui/tree.py
src/asm/cmsui/asset_templates/downloadaction.pt
src/asm/cmsui/asset_templates/imagepicker.pt
src/asm/cmsui/cms_templates/actions.pt
src/asm/cmsui/cms_templates/preview-window.pt
src/asm/cmsui/edition_templates/editions.pt
src/asm/cmsui/edition_templates/extendedpageactions.pt
src/asm/cmsui/edition_templates/imagepicker.pt
src/asm/cmsui/htmlpage_templates/extendedpageactions.pt
src/asm/cmsui/htmlpage_templates/index.pt
src/asm/cmsui/importer_templates/importactions.pt
src/asm/cmsui/layout_templates/breadcrumbs.pt
src/asm/cmsui/layout_templates/flashmessagenotification.pt
src/asm/cmsui/news_templates/index.pt
src/asm/cmsui/page_templates/actions.pt
src/asm/cmsui/page_templates/navigationactions.pt
src/asm/cmsui/public/__init__.py
src/asm/cmsui/public/layout.py
src/asm/cmsui/public/static/search.js
src/asm/cmsui/replace_templates/actions.pt
src/asm/cmsui/replace_templates/replacepreview.pt
src/asm/cmsui/replace_templates/searchandreplace.pt
src/asm/cmsui/search_templates/osdd.pt
src/asm/cmsui/search_templates/publicsearch.pt
src/asm/cmsui/search_templates/search.pt
src/asm/cmsui/static/async.min.js
src/asm/cmsui/static/cms.css
src/asm/cmsui/static/cms.js
src/asm/cmsui/static/favicon.ico
src/asm/cmsui/static/forms.css
src/asm/cmsui/static/jquery-1.4.3.min.js
src/asm/cmsui/static/jquery-1.7.1.min.js
