Metadata-Version: 1.0
Name: asm.cmsui
Version: 0.1.18
Summary: Assembly CMS - CMS UI package
Home-page: UNKNOWN
Author: Webcrew
Author-email: web@assembly.org
License: ZPL 2.1
Platform: UNKNOWN
